weblaze/__init__.py
weblaze/cli.py
weblaze/utils.py
weblaze-0.1.2.dist-info/LICENSE
weblaze-0.1.2.dist-info/METADATA
weblaze-0.1.2.dist-info/WHEEL
weblaze-0.1.2.dist-info/entry_points.txt
weblaze-0.1.2.dist-info/RECORD
