Metadata-Version: 2.1
Name: weblaze
Version: 0.1.2
Summary: 
Home-page: https://github.com/cybershang/weblaze
License: MIT
Keywords: backblaze,webp,cli
Author: Yingjie
Author-email: dev@yingjie.space
Requires-Python: >=3.12,<4.0
Classifier: Development Status :: 3 - Alpha
Classifier: Environment :: Console
Classifier: License :: OSI Approved :: MIT License
Classifier: Operating System :: OS Independent
Classifier: Programming Language :: Python :: 3
Classifier: Programming Language :: Python :: 3.12
Classifier: Topic :: Utilities
Requires-Dist: b2sdk (==1.31.0)
Requires-Dist: pyyaml (==6.0.1)
Requires-Dist: rich (>=13.7.0,<14.0.0)
Requires-Dist: typer (==0.9.0)
Project-URL: Repository, https://github.com/shangcode/weblaze
